{
  "categoryId": 23,
  "group": "افلام ومسلسلات",
  "title": "مسلسل بلاك كلوفر",
  "questions": [
    {
      "difficulty": "easy",
      "question": "ما هو الهدف الأساسي لأستا ويونو الذي يسعيان لتحقيقه؟",
      "answer": "أن يصبحا إمبراطور السحر"
    },
    {
      "difficulty": "easy",
      "question": "ما هو اسم الفرقة التي انضم إليها أستا؟",
      "answer": "الثيران السوداء"
    },
    {
      "difficulty": "easy",
      "question": "ما هو الاسم الذي يطلق على كتاب التعاويذ الخاص بأستا؟",
      "answer": "غريموار البرسيم خماسي الأوراق"
    },
    {
      "difficulty": "easy",
      "question": "ما هو نوع السحر الذي لا يستطيع أستا استخدامه على الإطلاق؟",
      "answer": "السحر العادي"
    },
    {
      "difficulty": "easy",
      "question": "ماذا كان أول اختبار واجهه أستا ويونو في يوم الاختبارات الانضمام لفرق الفرسان؟",
      "answer": "استخدام السحر الأساسي للطيران على مكنسة"
    },
    {
      "difficulty": "easy",
      "question": "ما هو الشيء الذي يخرج من غريموار أستا ويمكنه تبديد السحر؟",
      "answer": "سيف مضاد للسحر"
    },
    {
      "difficulty": "easy",
      "question": "ما هو لقب يونو في فرقة الفجر الذهبي؟",
      "answer": "نجم الأمل الجديد"
    },
    {
      "difficulty": "easy",
      "question": "ما هو اسم الوحش الشيطاني الذي ختم داخله؟",
      "answer": "ليف"
    },
    {
      "difficulty": "easy",
      "question": "ما هو اسم مملكة أستا ويونو؟",
      "answer": "مملكة كلوفر"
    },
    {
      "difficulty": "easy",
      "question": "ما هو نوع الغريموار الذي حصل عليه يونو في حفل منح الغريموار؟",
      "answer": "غريموار البرسيم رباعي الأوراق"
    },
    {
      "difficulty": "easy",
      "question": "ما هي المهمة الأولى التي ذهب إليها أستا ورفيقته نوال؟",
      "answer": "استكشاف كهف"
    },
    {
      "difficulty": "easy",
      "question": "ما هو اسم القائد الذي تبنى أستا ويونو؟",
      "answer": "الأب أورشيا"
    },
    {
      "difficulty": "easy",
      "question": "ما هو اسم الشخص الذي كان يقاتله أستا عندما ظهر للمرة الأولى سيفه المضاد للسحر؟",
      "answer": "ليبوتشي"
    },
    {
      "difficulty": "easy",
      "question": "ما هو اسم العضو في الثيران السوداء الذي لديه سحر الفضاء؟",
      "answer": "فينريال رولاكاس"
    },
    {
      "difficulty": "easy",
      "question": "ما هي العضو في الثيران السوداء التي تستخدم سحر الخيوط؟",
      "answer": "فانيسا إينوتيكا"
    },
    {
      "difficulty": "easy",
      "question": "ما هو نوع السحر الذي تستخدمه نوال سيلفا؟",
      "answer": "سحر الماء"
    },
    {
      "difficulty": "easy",
      "question": "ما هو اسم القارة التي تقع خارج حدود مملكة كلوفر وممالكها المجاورة؟",
      "answer": "القارة الغربية"
    },
    {
      "difficulty": "easy",
      "question": "ما هو هدف منظمة عين شمس منتصف الليل؟",
      "answer": "الانتقام من البشر"
    },
    {
      "difficulty": "easy",
      "question": "ما هو العنصر السحري الأساسي الذي يستخدمه يونو؟",
      "answer": "سحر الرياح"
    },
    {
      "difficulty": "easy",
      "question": "ما هي فرقة فرسان السحر التي يُعتبر قائدها الأقوى بين القادة؟",
      "answer": "الفجر الذهبي"
    },
    {
      "difficulty": "easy",
      "question": "ما هو الشيء الذي سرقه أستا ونوال من مخبأ عين شمس منتصف الليل؟",
      "answer": "حجر السحر"
    },
    {
      "difficulty": "easy",
      "question": "ما هي أول مهمة مشتركة بين أستا ويونو في مهمة إيجاد حجر السحر؟",
      "answer": "كهف المياه"
    },
    {
      "difficulty": "easy",
      "question": "ما هو اسم قائد فرقة الثيران السوداء؟",
      "answer": "يامي سوكيهيرو"
    },
    {
      "difficulty": "easy",
      "question": "ما هو مصدر قوة سحر يامي الأساسي؟",
      "answer": "سحر الظلام"
    },
    {
      "difficulty": "easy",
      "question": "ما هو الحدث الذي حصل فيه استبدال أجساد البشر بالجان؟",
      "answer": "إعادة تجسيد الجان"
    },
    {
      "difficulty": "easy",
      "question": "ما هو الشيء الذي كان يسعى إليه باتري (عين شمس منتصف الليل)؟",
      "answer": "إحياء الجان"
    },
    {
      "difficulty": "easy",
      "question": "ما هو اسم القرية التي نشأ فيها أستا ويونو؟",
      "answer": "قرية هاجي"
    },
    {
      "difficulty": "easy",
      "question": "ما هو الاسم الحقيقي لقائد فرقة عين شمس منتصف الليل؟",
      "answer": "باتري"
    },
    {
      "difficulty": "easy",
      "question": "ما هو الدور الذي تلعبه نيرو (السيل المانع)؟",
      "answer": "ختم الشياطين"
    },
    {
      "difficulty": "easy",
      "question": "ما هو الاسم الذي يطلقه أستا على نوال؟",
      "answer": "البقرة العضاضة"
    },
    {
      "difficulty": "easy",
      "question": "ما هي الفتاة التي انضمت إلى الثيران السوداء بعد معركة عين شمس منتصف الليل ولديها سحر الوقت؟",
      "answer": "سيكري سواناي"
    },
    {
      "difficulty": "easy",
      "question": "ما هو اسم الإمبراطور الحالي لسحر مملكة كلوفر؟",
      "answer": "يوليوس نوفاكرونو"
    },
    {
      "difficulty": "easy",
      "question": "ما هو نوع السحر الذي يستخدمه الإمبراطور الساحر يوليوس؟",
      "answer": "سحر الوقت"
    },
    {
      "difficulty": "easy",
      "question": "ما هو الشيء الذي يحتاجه يوليوس ليستعيد قوته الكاملة بعد قتاله مع باتري؟",
      "answer": "تراكم الوقت"
    },
    {
      "difficulty": "easy",
      "question": "ما هو اسم المملكة التي اشتهرت بأنها الأضعف في البداية؟",
      "answer": "مملكة هارت"
    },
    {
      "difficulty": "easy",
      "question": "ما هو اسم القارة التي تحتوي على الشياطين؟",
      "answer": "العالم السفلي"
    },
    {
      "difficulty": "easy",
      "question": "ما هي العضو في الثيران السوداء التي لديها سحر النار؟",
      "answer": "ماجنا سوينغ"
    },
    {
      "difficulty": "easy",
      "question": "ما هي الأداة التي يستخدمها أستا في معاركه لاستدعاء سيفيه؟",
      "answer": "غريموار البرسيم خماسي الأوراق"
    },
    {
      "difficulty": "easy",
      "question": "ما هو الشيء الذي سُرق من قصر العائلة المالكة في مهمة الحماية؟",
      "answer": "حجر السحر"
    },
    {
      "difficulty": "easy",
      "question": "ما هو الشيء الذي يميز الثيران السوداء عن باقي الفرق؟",
      "answer": "قلة النظام والتهور"
    },
    {
      "difficulty": "easy",
      "question": "ما هو الاسم الذي يطلقه باتري على نفسه عندما يتصرف كإنسان؟",
      "answer": "وليام فانجانس"
    },
    {
      "difficulty": "easy",
      "question": "ما هو اسم الفتاة التي تحب أستا ولديها سحر النبات؟",
      "answer": "ميموزا فيرميليون"
    },
    {
      "difficulty": "easy",
      "question": "ما هو اسم أحد السيوف التي يستخدمها أستا؟",
      "answer": "سيف كاتبون"
    },
    {
      "difficulty": "easy",
      "question": "ما هو اسم القائد الذي يمتلك سحر الدم؟",
      "answer": "جويل سيلفا"
    },
    {
      "difficulty": "easy",
      "question": "ما هو الشيء الذي تبحث عنه الثيران السوداء في مهمة كهف المياه؟",
      "answer": "حجر السحر"
    },
    {
      "difficulty": "easy",
      "question": "ما هي المدينة التي دمرت جزئياً بسبب هجوم باتري؟",
      "answer": "مدينة العاصمة الملكية"
    },
    {
      "difficulty": "easy",
      "question": "ما هو اسم الشرير الذي كان يسيطر على باتري في البداية؟",
      "answer": "شيطان زاجريد"
    },
    {
      "difficulty": "easy",
      "question": "ما هو الشيء الذي يمنح فرسان السحر قوتهم الأساسية؟",
      "answer": "المانا"
    },
    {
      "difficulty": "easy",
      "question": "ما هو العنصر الذي يستحوذ عليه يونو بصفة أساسية؟",
      "answer": "الرياح"
    },
    {
      "difficulty": "easy",
      "question": "ما هو اسم القرية التي هوجمت من قبل جماعة عين شمس منتصف الليل في البداية؟",
      "answer": "قرية ساوساي"
    },
    {
      "difficulty": "easy",
      "question": "ما هو اسم القلادة التي كان يحملها يونو؟",
      "answer": "هدية من الأب أورشيا"
    },
    {
      "difficulty": "easy",
      "question": "ما هو الشيء الذي يمنح أستا قوته؟",
      "answer": "افتقاره للسحر"
    },
    {
      "difficulty": "easy",
      "question": "ما هو اسم القائد الذي يمتلك سحر الصلب؟",
      "answer": "فويغولينج فيرميليون"
    },
    {
      "difficulty": "easy",
      "question": "ما هو اسم الشرير الذي ظهر في مهمة الغابة الساحرة؟",
      "answer": "فانجيزا"
    },
    {
      "difficulty": "easy",
      "question": "ما هو الشيء الذي يفعله أستا عندما يصرخ؟",
      "answer": "يشجع نفسه"
    },
    {
      "difficulty": "easy",
      "question": "ما هو الشيء الذي يخاف منه الكثيرون في مملكة كلوفر؟",
      "answer": "الشياطين"
    },
    {
      "difficulty": "easy",
      "question": "ما هو اسم الشرير الذي لديه سحر اللهب الأسود؟",
      "answer": "رايا"
    },
    {
      "difficulty": "easy",
      "question": "ما هو الشيء الذي كان يهدف إليه الأب أورشيا في تربية الأطفال؟",
      "answer": "زرع الأمل"
    },
    {
      "difficulty": "easy",
      "question": "ما هو اسم العضو في الثيران السوداء الذي لديه سحر المرايا؟",
      "answer": "جوش رولاكاس"
    },
    {
      "difficulty": "easy",
      "question": "ما هي العضو في الثيران السوداء التي لديها سحر الدخان؟",
      "answer": "تشارمي بابيتسون"
    },
    {
      "difficulty": "easy",
      "question": "ما هي المدينة التي توجد فيها أكاديمية تدريب فرسان السحر؟",
      "answer": "العاصمة الملكية"
    },
    {
      "difficulty": "easy",
      "question": "ما هو اسم الساحر الذي تمكن من ختم الشيطان لأول مرة؟",
      "answer": "أول إمبراطور سحر"
    },
    {
      "difficulty": "easy",
      "question": "ما هو اسم الكائن الذي يسكن داخل غريموار أستا؟",
      "answer": "الشيطان ليف"
    },
    {
      "difficulty": "easy",
      "question": "ما هو اسم القائد الذي لديه سحر الجليد؟",
      "answer": "نواه سيلفا"
    },
    {
      "difficulty": "easy",
      "question": "ما هو الشيء الذي يجمع بين الثيران السوداء في مقرهم؟",
      "answer": "الطعام الفوضوي"
    },
    {
      "difficulty": "easy",
      "question": "ما هو اسم المكان الذي يحوي سيف أستا الثالث؟",
      "answer": "برج السحر"
    },
    {
      "difficulty": "easy",
      "question": "ما هو الاسم الذي يطلقه يامي على هجماته القوية؟",
      "answer": "سحر الظلام: القطع المظلم"
    },
    {
      "difficulty": "easy",
      "question": "ما هو الاسم الذي يطلقه أستا على سيفه الأول؟",
      "answer": "سيف ديمون سلاير"
    },
    {
      "difficulty": "easy",
      "question": "ما هو الشيء الذي يميز نوال عن أفراد عائلتها؟",
      "answer": "أنها لا تستطيع التحكم في سحرها في البداية"
    },
    {
      "difficulty": "easy",
      "question": "ما هو اسم القائد الذي لديه سحر التبلور؟",
      "answer": "كوبرا فيرميليون"
    },
    {
      "difficulty": "easy",
      "question": "ما هي الفتاة التي كانت تحب قائد فرقة الفجر الذهبي؟",
      "answer": "ليتشي"
    },
    {
      "difficulty": "easy",
      "question": "ما هو الاسم الذي يُطلق على الأشخاص الذين يمتلكون سحرًا قويًا؟",
      "answer": "الأفراد السحريون"
    },
    {
      "difficulty": "easy",
      "question": "ما هو الشيء الذي أراد باتري (الجان) أن يعيده إلى الحياة؟",
      "answer": "قرية الجان"
    },
    {
      "difficulty": "easy",
      "question": "ما هو اسم القارة التي تقع فيها مملكة كلوفر؟",
      "answer": "مملكة الأربعة"
    },
    {
      "difficulty": "easy",
      "question": "ما هو اسم القائد الذي لديه سحر الرمل؟",
      "answer": "فوغوليون سيلفا"
    },
    {
      "difficulty": "easy",
      "question": "ما هو اسم العضو في الثيران السوداء الذي يمتلك سحر الإشعاع؟",
      "answer": "زورا إيديال"
    },
    {
      "difficulty": "easy",
      "question": "ما هو الشيء الذي يجمع بين جميع أعضاء الثيران السوداء؟",
      "answer": "أنهم جميعاً منبوذون"
    },
    {
      "difficulty": "easy",
      "question": "ما هو الاسم الذي يطلقه أستا على ليف عندما يتكلم معه؟",
      "answer": "الشقي الصغير"
    },
    {
      "difficulty": "easy",
      "question": "ما هو الشيء الذي كان هدفًا لغارة مملكة دايموند على مملكة كلوفر؟",
      "answer": "السيطرة على الحدود"
    },
    {
      "difficulty": "easy",
      "question": "ما هو اسم الشخصية التي تحولت إلى طفل بعد قتالها مع باتري؟",
      "answer": "يوليوس نوفاكرونو"
    },
    {
      "difficulty": "easy",
      "question": "ما هو الشيء الذي يحصل عليه فرسان السحر عند الانضمام للفرقة؟",
      "answer": "عباءة الفرقة"
    },
    {
      "difficulty": "easy",
      "question": "ما هو اسم القائد الذي لديه سحر النيران؟",
      "answer": "ليوبولد فيرميليون"
    },
    {
      "difficulty": "easy",
      "question": "ما هو اسم المنطقة التي تحوي الغابة الساحرة؟",
      "answer": "الحدود البعيدة"
    },
    {
      "difficulty": "easy",
      "question": "ما هو اسم الشرير الذي كان يلاحق أستا لنزع السحر منه؟",
      "answer": "ريتو"
    },
    {
      "difficulty": "easy",
      "question": "ما هو الشيء الذي تستخدمه نوال في نهاية معاركها القوية؟",
      "answer": "درع مائي قوي"
    },
    {
      "difficulty": "easy",
      "question": "ما هو اسم القائد الذي لديه سحر البرق؟",
      "answer": "كابتن الفجر الذهبي"
    },
    {
      "difficulty": "easy",
      "question": "ما هو الشيء الذي كان يفعله أستا عندما كان صغيرًا لإثارة إعجاب يونو؟",
      "answer": "التدريب البدني"
    },
    {
      "difficulty": "easy",
      "question": "ما هو اسم العضو في الثيران السوداء الذي لديه سحر الأشباح؟",
      "answer": "جوشوا"
    },
    {
      "difficulty": "easy",
      "question": "ما هو الاسم الذي يُطلق على السحر الذي يستخدمه أستا؟",
      "answer": "سحر مضاد للسحر"
    },
    {
      "difficulty": "easy",
      "question": "ما هو الشيء الذي كان يكرهه أفراد العائلة المالكة في نوال؟",
      "answer": "عدم قدرتها على التحكم في سحرها"
    },
    {
      "difficulty": "easy",
      "question": "ما هو اسم الشرير الذي كان يملك سحر الدمى؟",
      "answer": "ماريون"
    },
    {
      "difficulty": "easy",
      "question": "ما هو اسم المدينة التي تم استعادتها بعد هجوم عين شمس منتصف الليل؟",
      "answer": "مدينة كلوفر"
    },
    {
      "difficulty": "easy",
      "question": "ما هو اسم الشرير الذي كان يملك سحر التعويذات؟",
      "answer": "ريفا"
    },
    {
      "difficulty": "easy",
      "question": "ما هو الشيء الذي يميز غريموار أستا عن غريموارات الآخرين؟",
      "answer": "أن غريمواره مدمر وممزق"
    },
    {
      "difficulty": "easy",
      "question": "ما هو الشيء الذي كان يستخدمه ليخت لتوصيل الرسائل إلى باتري؟",
      "answer": "التعاويذ"
    },
    {
      "difficulty": "easy",
      "question": "ما هو الاسم الذي يطلقه أستا على نوال عندما يصرخ عليها؟",
      "answer": "نوال الصارخة"
    },
    {
      "difficulty": "easy",
      "question": "ما هو اسم الشرير الذي يمتلك سحر الوقت المتقدم؟",
      "answer": "باتري"
    },
    {
      "difficulty": "easy",
      "question": "ما هو الشيء الذي كان يطمح إليه يونو منذ الصغر؟",
      "answer": "أن يصبح إمبراطور السحر"
    },
    {
      "difficulty": "easy",
      "question": "ما هو اسم المنطقة التي تسيطر عليها مملكة هارت؟",
      "answer": "منطقة هارت"
    },
    {
      "difficulty": "easy",
      "question": "ما هو الشيء الذي كان يستخدمه باتري لإعادة تجسيد الجان؟",
      "answer": "أحجار السحر"
    },
    {
      "difficulty": "medium",
      "question": "ما هي الأحداث التي أدت إلى فقدان يوليوس نوفاكرونو لجزء كبير من قوته؟",
      "answer": "قتاله ضد باتري وتلقيه لضربة قاضية"
    },
    {
      "difficulty": "medium",
      "question": "ما هو المفهوم الذي يسمح لأستا بتبديد تعاويذ الخصوم باستخدام سيوفه؟",
      "answer": "سحر المضاد للسحر الذي يلغي التعاويذ السحرية"
    },
    {
      "difficulty": "medium",
      "question": "ما هو الشرط الذي يجب على أستا تحقيقه ليتمكن من استخدام قوة الشيطان ليف لفترة أطول؟",
      "answer": "إبرام عقد معه وتطوير اندماجهما"
    },
    {
      "difficulty": "medium",
      "question": "ما هو الاسم الذي يطلق على السيف الذي يستخدمه أستا لقطع وتفريق الروابط السحرية؟",
      "answer": "سيف الشياطين"
    },
    {
      "difficulty": "medium",
      "question": "ما هو الدور الذي لعبته نيرو في ختم الشيطان الأول؟",
      "answer": "كانت رفيقة الإمبراطور الساحر الأول واستخدمت سحر الختم"
    },
    {
      "difficulty": "medium",
      "question": "ما هو التحدي الذي واجهته نوال خلال مهمة معبد تحت الماء؟",
      "answer": "تعلم كيفية التحكم في سحرها الهائل وإنشاء درع مائي"
    },
    {
      "difficulty": "medium",
      "question": "ما هو سر قوة قائد فرقة الفجر الذهبي ويليام فانجانس؟",
      "answer": "أنه يمتلك جسدين وروحين"
    },
    {
      "difficulty": "medium",
      "question": "ما هي التقنية المتقدمة في استخدام المانا التي يتم تدريب أستا ويونو عليها؟",
      "answer": "مانازون التي تسمح بالتحكم في المانا المحيطة"
    },
    {
      "difficulty": "medium",
      "question": "ما هو اسم الشخصية التي استولى عليها شيطان الزاجريد؟",
      "answer": "باتري"
    },
    {
      "difficulty": "medium",
      "question": "ما هي الكيفية التي تمكن بها يامي من استخدام سحر الظلام كسحر إطلاق نار؟",
      "answer": "من خلال سحر الختم المظلم"
    },
    {
      "difficulty": "medium",
      "question": "ما هو السر وراء قوة أعضاء عائلة سيلفا؟",
      "answer": "امتلاكهم لكميات هائلة من المانا وسحر الماء"
    },
    {
      "difficulty": "medium",
      "question": "ما هو السبب الذي جعل أستا يتجه نحو تعلم فنون القتال الجسدي؟",
      "answer": "لأنه ولد بلا سحر على الإطلاق"
    },
    {
      "difficulty": "medium",
      "question": "ما هي الأحداث التي سبقت ظهور سيف أستا الثاني؟",
      "answer": "قتاله ضد فانايا في كهف المياه"
    },
    {
      "difficulty": "medium",
      "question": "ما هو النظام الذي تستخدمه مملكة هارت لتصنيف قوة فرسان السحر؟",
      "answer": "نظام الماجيماستر"
    },
    {
      "difficulty": "medium",
      "question": "ما هو التحدي الذي واجهه أستا خلال مهمة الغابة الساحرة؟",
      "answer": "قتال الساحرة الأم التي أرادت استخدام أستا"
    },
    {
      "difficulty": "medium",
      "question": "ما هو نوع السحر الذي تمكنت نيرو من إيقافه عن الحركة؟",
      "answer": "سحر الختم"
    },
    {
      "difficulty": "medium",
      "question": "ما هو الاسم الذي يطلق على المكان الذي يتم فيه تدريب فرسان السحر على التحكم في المانا؟",
      "answer": "غابة المانا"
    },
    {
      "difficulty": "medium",
      "question": "ما هي القوة الجديدة التي اكتشفها يونو بعد حصوله على غريموار البرسيم رباعي الأوراق؟",
      "answer": "قوة الرياح الروحية"
    },
    {
      "difficulty": "medium",
      "question": "ما هو الشيء الذي يميز سحر عائلة فيرميليون؟",
      "answer": "امتلاكهم لسحر النيران القوي"
    },
    {
      "difficulty": "medium",
      "question": "ما هي الأحداث التي كشفت أن باتري ليس الشرير الرئيسي؟",
      "answer": "ظهور شيطان الزاجريد واستخدامه لباتري"
    },
    {
      "difficulty": "medium",
      "question": "ما هو نوع السحر الذي يستخدمه يامي لمواجهة السحر المضاد؟",
      "answer": "سحر الظلام"
    },
    {
      "difficulty": "medium",
      "question": "ما هي الأداة التي استخدمها يوليوس لإيقاف هجوم باتري القوي؟",
      "answer": "تعويذة وقت متقدمة"
    },
    {
      "difficulty": "medium",
      "question": "ما هو السبب الذي دفع نوال إلى الانضمام لفرقة الثيران السوداء؟",
      "answer": "شعورها بالنبذ من عائلتها الملكية"
    },
    {
      "difficulty": "medium",
      "question": "ما هو الحدث الذي أدى إلى إصابة فوغولينج بفقدان ذراعيه؟",
      "answer": "هجوم مفاجئ من عين شمس منتصف الليل"
    },
    {
      "difficulty": "medium",
      "question": "ما هي الكيفية التي تمكن بها أستا من تبديد سحر الختم الذي كان يمنع الساحرة الأم؟",
      "answer": "بسيفه المضاد للسحر"
    },
    {
      "difficulty": "medium",
      "question": "ما هو الشيء الذي سُرق من الإمبراطور الساحر يوليوس في بداية القصة؟",
      "answer": "تعويذة خريطة سحرية"
    },
    {
      "difficulty": "medium",
      "question": "ما هو السبب الذي جعل يامي يستعين بأستا ونوال في مهمة كهف المياه؟",
      "answer": "لتبديد سحر فانايا القوي"
    },
    {
      "difficulty": "medium",
      "question": "ما هو الاسم الذي يطلق على شكل أستا الذي يندمج فيه مع الشيطان؟",
      "answer": "شكل الشيطان"
    },
    {
      "difficulty": "medium",
      "question": "ما هو الدور الذي لعبته فانيسا في حماية أستا؟",
      "answer": "استخدام سحر الخيوط لتغيير مصيره"
    },
    {
      "difficulty": "medium",
      "question": "ما هو نوع السحر الذي يستخدمه باتري بشكل أساسي؟",
      "answer": "سحر الضوء"
    },
    {
      "difficulty": "medium",
      "question": "ما هو الاسم الذي يطلق على المنطقة المحظورة التي توجد فيها الشياطين؟",
      "answer": "الزونجاي"
    },
    {
      "difficulty": "medium",
      "question": "ما هي الأحداث التي أدت إلى ظهور شكل يونو المدمج مع روح الريح؟",
      "answer": "قتاله ضد أحد أعضاء الجان في معركة إحياء الجان"
    },
    {
      "difficulty": "medium",
      "question": "ما هو الشيء الذي كان يسعى إليه الشرير رايا؟",
      "answer": "استخدام سحر النسخ لتجسيد قوة الجان"
    },
    {
      "difficulty": "medium",
      "question": "ما هو التحدي الذي واجهته نوال في قتالها ضد أختها ميموزا؟",
      "answer": "إثبات أن قوتها تفوق قوة السحر الملكي"
    },
    {
      "difficulty": "medium",
      "question": "ما هي الكيفية التي تمكن بها يامي من سحب أستا من عالم الشياطين؟",
      "answer": "باستخدام سحر الظلام الخاص به"
    },
    {
      "difficulty": "medium",
      "question": "ما هو الاسم الذي يطلق على شكل أستا عندما يمتلك سيفاً ثالثاً؟",
      "answer": "شكل إله الشر"
    },
    {
      "difficulty": "medium",
      "question": "ما هو الشرط الذي كان يجب على أستا تحقيقه لدخول معبد المياه؟",
      "answer": "أن يكون شخصاً غير ساحر"
    },
    {
      "difficulty": "medium",
      "question": "ما هي القوة التي اكتشفها يونو مؤخراً بعد حصوله على قوة الجان؟",
      "answer": "سحر الضوء"
    },
    {
      "difficulty": "medium",
      "question": "ما هو الشيء الذي كان يستخدمه شيطان الزاجريد للسيطرة على باتري؟",
      "answer": "تعويذة الختم السحري"
    },
    {
      "difficulty": "medium",
      "question": "ما هي الكيفية التي تمكن بها أستا من إنقاذ يامي من سحر الإحياء؟",
      "answer": "بتبديد سحر الإحياء باستخدام سيفه"
    },
    {
      "difficulty": "medium",
      "question": "ما هو التحدي الذي واجهه أستا خلال مهمة مملكة دايموند؟",
      "answer": "قتال ساحر قوي يمتلك سحر الزئبق"
    },
    {
      "difficulty": "hard",
      "question": "ما هي الآلية الدقيقة التي سمحت لسحر المضاد للسحر بتبديد سحر الإحياء دون قتل البشر؟",
      "answer": "سيف كاتاون يمكنه فصل وإلغاء التعاويذ المعقدة دون إيذاء الكيان المادي"
    },
    {
      "difficulty": "hard",
      "question": "ما هو السبب الجوهري الذي جعل باتري يستجيب لشيطان زاجريد؟",
      "answer": "لأن زاجريد وعد باتري بالقدرة على إحياء قبيلة الجان بالكامل"
    },
    {
      "difficulty": "hard",
      "question": "ما هي العلاقة المعقدة بين قوة سحر الظلام ليامي وقوة عالم الشياطين؟",
      "answer": "سحر الظلام هو سحر حدودي يمكنه جذب الأبعاد"
    },
    {
      "difficulty": "hard",
      "question": "ما هي الآلية المتقدمة التي يستخدمها يوليوس للسفر عبر الزمن في قتاله ضد باتري؟",
      "answer": "يستخدم سحر الوقت لتخزين الوقت في الأوراق"
    },
    {
      "difficulty": "hard",
      "question": "ما هو التطور الدقيق الذي حدث لقوة نوال لتمكينها من إتقان فالكري آرمور؟",
      "answer": "إتقانها لمانا سكين على جسدها وثقتها الكاملة بقوتها"
    },
    {
      "difficulty": "hard",
      "question": "ما هي العملية التي يخضع لها أستا لزيادة وقت استخدامه لقوة الشيطان؟",
      "answer": "تدريب اليونيون الذي يزيد من توافقه مع الشيطان"
    },
    {
      "difficulty": "hard",
      "question": "ما هو نوع سحر شيطان الزاجريد وما هي طبيعة التعويذة التي استخدمها؟",
      "answer": "سحر الكلمات الشيطانية الذي يمكنه تشكيل أي شيء"
    },
    {
      "difficulty": "hard",
      "question": "ما هو الاسم الذي يطلق على القوة السرية التي يمتلكها يونو كإرث لليخت؟",
      "answer": "قوة البرسيم الرباعي الحقيقية"
    },
    {
      "difficulty": "hard",
      "question": "ما هو الدور الذي لعبته سيكري في إنشاء مملكة كلوفر؟",
      "answer": "كانت رفيقة الإمبراطور الساحر الأول وساعدته في ختم الشيطان"
    },
    {
      "difficulty": "hard",
      "question": "ما هو المفهوم الذي يصف قدرة يامي في الدخول إلى مانا زون بشكل طبيعي؟",
      "answer": "أنه من قارة مختلفة مما يمنحه إتقاناً طبيعياً"
    },
    {
      "difficulty": "hard",
      "question": "ما هي الآلية الدقيقة التي سمحت للشيطان ليف بالدخول لغريموار أستا؟",
      "answer": "الغريموار خماسي الأوراق ينشأ عندما يفسد غريموار برسيم رباعي الأوراق"
    },
    {
      "difficulty": "hard",
      "question": "ما هو السبب الحقيقي وراء محاولة رايا لنسخ سحر المضاد للسحر؟",
      "answer": "لنسخ القوة التي تتبدد السحر لتحقيق أهدافهم"
    },
    {
      "difficulty": "hard",
      "question": "ما هو الشيء الذي يميز سحر الظلام ليامي عن سحر الظلام العادي؟",
      "answer": "أنه مرتبط بقوة جسده وقدرته على سحب الأعداء نحو بعد آخر"
    },
    {
      "difficulty": "hard",
      "question": "ما هي الظروف التي سمحت لليخت بتبديد السحر المضاد الذي كان مسيطراً على أستا؟",
      "answer": "باستخدام سحر الضوء النقي والمضاد للسحر"
    },
    {
      "difficulty": "hard",
      "question": "ما هي الآلية التي سمحت لباتري بخداع الجان في البداية؟",
      "answer": "استخدم أحجار السحر كأداة لتضخيم سحر الإحياء"
    },
    {
      "difficulty": "hard",
      "question": "ما هو الاسم الذي يطلق على السيف الذي يمتلك القدرة على إخراج السحر الشيطاني؟",
      "answer": "سيف تبديد السحر"
    },
    {
      "difficulty": "hard",
      "question": "ما هو التحدي الذي واجهه أستا ويونو في تدريب مانا زون المتقدم؟",
      "answer": "استخدام المانا المحيطة بفاعلية دون الاعتماد على المانا الداخلية"
    },
    {
      "difficulty": "hard",
      "question": "ما هي الآلية التي سمحت لنوال بتحرير طاقتها السحرية الضخمة؟",
      "answer": "تطويرها لقدرة فالكري آرمور التي تقوم بوظيفة الختم والتحكم"
    },
    {
      "difficulty": "hard",
      "question": "ما هو الشيء الذي يميز سحر عائلة فيرميليون عن سحر النيران العادي؟",
      "answer": "أن نيرانهم أقوى وأكثر كثافة ويمكن أن تتخذ أشكالاً معقدة"
    },
    {
      "difficulty": "hard",
      "question": "ما هو الحدث الذي كشف عن العلاقة الوثيقة بين ويليام وباتري؟",
      "answer": "ظهورهما معاً في قتال يوليوس وكشف باتري عن أنه يستخدم جسد ويليام"
    },
    {
      "difficulty": "hard",
      "question": "ما هو الاسم الذي يطلق على شكل أستا الذي يندمج فيه بالكامل مع الشيطان؟",
      "answer": "شكل الاتحاد"
    },
    {
      "difficulty": "hard",
      "question": "ما هي الآلية التي سمحت لفانيسا بتغيير مصير أستا في قتاله؟",
      "answer": "استخدام خيط القدر الذي يعيد تشكيل الأحداث السلبية"
    },
    {
      "difficulty": "hard",
      "question": "ما هو السر وراء سحر سيكري وكيف يمكنها استخدامه لختم الشياطين؟",
      "answer": "سحر الختم هو سحر نادر يمكنه حبس الكائنات السحرية القوية"
    },
    {
      "difficulty": "hard",
      "question": "ما هو الاسم الذي يطلق على السحر الذي يستخدمه يوليوس لتغيير الزمن؟",
      "answer": "سحر الوقت"
    },
    {
      "difficulty": "hard",
      "question": "ما هي الكيفية التي تمكن بها يونو من دمج قوة الجان مع روح الريح؟",
      "answer": "دمج سحر الرياح مع طاقة روح الريح لإنشاء هجمات روحية"
    },
    {
      "difficulty": "hard",
      "question": "ما هو الاسم الذي يطلق على الهجوم الذي استخدمه يامي لقطع الزاجريد؟",
      "answer": "سحر الظلام: القطع المظلم"
    },
    {
      "difficulty": "hard",
      "question": "ما هي الآلية التي سمحت لأستا بتبديد سحر الإحياء الذي كان يسيطر على ليخت؟",
      "answer": "سيف كاتاون الذي يستطيع فصل الروابط السحرية المعقدة"
    },
    {
      "difficulty": "hard",
      "question": "ما هو الاسم الذي يطلق على السيف الذي يستخدمه أستا لامتصاص السحر؟",
      "answer": "سيف ديمون ديولير"
    },
    {
      "difficulty": "hard",
      "question": "ما هو الشيء الذي يميز مانا زون يامي عن باقي فرسان السحر؟",
      "answer": "أنها منطقة من الظلام تسمح له بإطلاق هجمات من أي مكان"
    }
  ]
}